{
"meta":{"test_sets":[],"test_metrics":[],"learn_metrics":[{"best_value":"Min","name":"MultiClass"}],"launch_mode":"Train","parameters":"","iteration_count":10,"learn_sets":["learn"],"name":"experiment"},
"iterations":[
{"learn":[0.9923745496],"iteration":0,"passed_time":0.1286650254,"remaining_time":1.157985228},
{"learn":[0.908081736],"iteration":1,"passed_time":0.210450416,"remaining_time":0.8418016642},
{"learn":[0.841763554],"iteration":2,"passed_time":0.2868891694,"remaining_time":0.6694080619},
{"learn":[0.7880024485],"iteration":3,"passed_time":0.3977895521,"remaining_time":0.5966843282},
{"learn":[0.7446205251],"iteration":4,"passed_time":0.4758822098,"remaining_time":0.4758822098},
{"learn":[0.7070997177],"iteration":5,"passed_time":0.5616909705,"remaining_time":0.374460647},
{"learn":[0.6758022349],"iteration":6,"passed_time":0.6545590251,"remaining_time":0.2805252965},
{"learn":[0.6501024729],"iteration":7,"passed_time":0.7372819485,"remaining_time":0.1843204871},
{"learn":[0.6271992931],"iteration":8,"passed_time":0.8271439772,"remaining_time":0.09190488635},
{"learn":[0.6083200162],"iteration":9,"passed_time":0.9227012415,"remaining_time":0}
]}